LICENSE
MANIFEST.in
README.md
setup.py
bearer_auth/__init__.py
bearer_auth/admin.py
bearer_auth/apps.py
bearer_auth/authentication.py
bearer_auth/models.py
bearer_auth/serializers.py
bearer_auth/settings.py
bearer_auth/urls.py
bearer_auth/views.py
bearer_auth/migrations/0001_initial.py
bearer_auth/migrations/__init__.py
django_rest_auth_bearer.egg-info/PKG-INFO
django_rest_auth_bearer.egg-info/SOURCES.txt
django_rest_auth_bearer.egg-info/dependency_links.txt
django_rest_auth_bearer.egg-info/requires.txt
django_rest_auth_bearer.egg-info/top_level.txt